avocavo_nutrition/__init__.py
avocavo_nutrition/auth.py
avocavo_nutrition/auth_supabase.py
avocavo_nutrition/client.py
avocavo_nutrition/exceptions.py
avocavo_nutrition/models.py
avocavo_nutrition-2.1.7.dist-info/licenses/LICENSE
avocavo_nutrition-2.1.7.dist-info/METADATA
avocavo_nutrition-2.1.7.dist-info/WHEEL
avocavo_nutrition-2.1.7.dist-info/top_level.txt
avocavo_nutrition-2.1.7.dist-info/RECORD
