Metadata-Version: 2.4
Name: avocavo-nutrition
Version: 2.1.7
Summary: Python SDK for the Avocavo Nutrition API - Fast, accurate nutrition data with USDA verification
Home-page: https://github.com/avocavo/nutrition-api-python
Download-URL: https://pypi.org/project/avocavo-nutrition/
Author: Avocavo
Author-email: Avocavo <support@avocavo.com>
License: MIT
Project-URL: Homepage, https://github.com/avocavo/nutrition-api-python
Project-URL: Documentation, https://nutrition.avocavo.app/docs/python
Project-URL: API Dashboard, https://nutrition.avocavo.app
Project-URL: Bug Tracker, https://github.com/avocavo/nutrition-api-python/issues
Project-URL: Changelog, https://github.com/avocavo/nutrition-api-python/blob/main/CHANGELOG.md
Keywords: nutrition,api,usda,food,recipe,health,fitness,calories,macros,nutrients,fooddata,fdc,cooking,meal-planning,diet,wellness,restaurant,food-tech
Platform: any
Classifier: Development Status :: 5 - Production/Stable
Classifier: Intended Audience :: Developers
Classifier: Intended Audience :: Healthcare Industry
Classifier: Intended Audience :: Science/Research
Classifier: Topic :: Software Development :: Libraries :: Python Modules
Classifier: Topic :: Scientific/Engineering :: Information Analysis
Classifier: Topic :: Internet :: WWW/HTTP :: Dynamic Content
Classifier: Topic :: Database :: Front-Ends
Classifier: License :: OSI Approved :: MIT License
Classifier: Programming Language :: Python :: 3
Classifier: Programming Language :: Python :: 3.7
Classifier: Programming Language :: Python :: 3.8
Classifier: Programming Language :: Python :: 3.9
Classifier: Programming Language :: Python :: 3.10
Classifier: Programming Language :: Python :: 3.11
Classifier: Programming Language :: Python :: 3.12
Classifier: Operating System :: OS Independent
Classifier: Natural Language :: English
Requires-Python: >=3.7
License-File: LICENSE
Requires-Dist: requests>=2.25.0
Requires-Dist: keyring>=23.0.0
Requires-Dist: supabase>=2.8.0
Provides-Extra: dev
Requires-Dist: pytest>=6.0; extra == "dev"
Requires-Dist: pytest-cov>=2.0; extra == "dev"
Requires-Dist: black>=21.0; extra == "dev"
Requires-Dist: flake8>=3.8; extra == "dev"
Requires-Dist: mypy>=0.800; extra == "dev"
Requires-Dist: twine>=3.0; extra == "dev"
Requires-Dist: wheel>=0.36; extra == "dev"
Provides-Extra: test
Requires-Dist: pytest>=6.0; extra == "test"
Requires-Dist: pytest-mock>=3.0; extra == "test"
Requires-Dist: responses>=0.18.0; extra == "test"
Requires-Dist: pytest-asyncio>=0.18.0; extra == "test"
Provides-Extra: docs
Requires-Dist: sphinx>=4.0; extra == "docs"
Requires-Dist: sphinx-rtd-theme>=1.0; extra == "docs"
Requires-Dist: myst-parser>=0.17; extra == "docs"
Dynamic: author
Dynamic: download-url
Dynamic: home-page
Dynamic: license-file
Dynamic: platform
Dynamic: requires-python
